odoo/addons/hr_expense_remove_mobile_link/README.rst
odoo/addons/hr_expense_remove_mobile_link/__init__.py
odoo/addons/hr_expense_remove_mobile_link/__manifest__.py
odoo/addons/hr_expense_remove_mobile_link/i18n/hr_expense_remove_mobile_link.pot
odoo/addons/hr_expense_remove_mobile_link/i18n/it.po
odoo/addons/hr_expense_remove_mobile_link/readme/CONTRIBUTORS.rst
odoo/addons/hr_expense_remove_mobile_link/readme/DESCRIPTION.rst
odoo/addons/hr_expense_remove_mobile_link/static/description/icon.png
odoo/addons/hr_expense_remove_mobile_link/static/description/index.html
odoo/addons/hr_expense_remove_mobile_link/views/hr_expense.xml
odoo14_addon_hr_expense_remove_mobile_link-14.0.1.0.1.dev4.dist-info/METADATA
odoo14_addon_hr_expense_remove_mobile_link-14.0.1.0.1.dev4.dist-info/WHEEL
odoo14_addon_hr_expense_remove_mobile_link-14.0.1.0.1.dev4.dist-info/top_level.txt
odoo14_addon_hr_expense_remove_mobile_link-14.0.1.0.1.dev4.dist-info/RECORD
